{
  "AutoReload": {
    "Timer1": 1773871200000,
    "Timer2": 1773835200000,
    "Timers": {
      "09:00": true,
      "19:00": true
    },
    "Enabled": false,
    "RecurringTime": 43200000
  },
  "CityColorHex": "#F82A2A",
  "Wipe": {
    "StartBank": 20000,
    "Password": "Reborn",
    "StartId": 1
  },
  "ServerName": "Reborn Studios",
  "Needs": {
    "Fome": 1,
    "Sede": 1,
    "Tempo": 90
  },
  "Identifier": "steam",
  "Theme": "default",
  "MaxHealth": 400,
  "NpcControl": {
    "PedDensity": 0.5,
    "VehicleDensity": 0.4,
    "ParkedVehicle": 0.2
  },
  "Discord": "https://discord.gg/8unYr9MUdx",
  "Maintenance": {
    "text": "Manutenção em andamento...",
    "licenses": {},
    "enabled": false
  },
  "Debug": false,
  "CityColor": "rgb(248, 42, 42)",
  "CityLogo": "https://api.rebornsystem.com.br/imagens/RebornLogo.png",
  "Whitelist": false
}
